{"language": "ru", "resources": [{"id": "res_224", "name": "1000", "description": "3000. 0. 4000", "eligibility": ""}, {"id": "res_225", "name": "3300", "description": "$2,275*. 0. 5575", "eligibility": ""}, {"id": "res_226", "name": "$7,800+", "description": "$3,000*. 0. $10,800+", "eligibility": ""}, {"id": "res_227", "name": "$1,200–$2,000", "description": "3000. $7,000–$15,000. $11,200–$20,000", "eligibility": ""}, {"id": "res_228", "name": "8400", "description": "$2,800*. 9450. 20650", "eligibility": ""}, {"id": "res_295", "name": "Hero Healthcare Equipment Recycling", "description": "HERO Cares", "eligibility": ""}, {"id": "res_304", "name": "Whirlwind Wheelchair", "description": "Roughrider", "eligibility": ""}, {"id": "res_405", "name": "A Mother's Rest", "description": "A Mothers Rest", "eligibility": ""}, {"id": "res_497", "name": "~304", "description": "", "eligibility": ""}]}